announcements/__init__.py
announcements/admin.py
announcements/auth_backends.py
announcements/forms.py
announcements/models.py
announcements/signals.py
announcements/urls.py
announcements/views.py
announcements/migrations/0001_initial.py
announcements/migrations/0002_auto_20200311_0959.py
announcements/migrations/__init__.py
announcements/templates/announcements/announcement_confirm_delete.html
announcements/templates/announcements/announcement_form.html
announcements/templates/announcements/announcement_list.html
announcements/templates/announcements/base.html
announcements/templatetags/__init__.py
announcements/templatetags/announcements_tags.py
geonode_announcements-2.0.2.1.dist-info/AUTHORS
geonode_announcements-2.0.2.1.dist-info/LICENSE
geonode_announcements-2.0.2.1.dist-info/METADATA
geonode_announcements-2.0.2.1.dist-info/WHEEL
geonode_announcements-2.0.2.1.dist-info/top_level.txt
geonode_announcements-2.0.2.1.dist-info/RECORD
