Metadata-Version: 2.1
Name: geonode-announcements
Version: 2.0.2.1
Summary: Fork of pinax/django-announcements. Announcements for your Django powered website.
Home-page: https://github.com/GeoNode/geonode-announcements
Author: Brian Rosner
Author-email: brosner@gmail.com
License: MIT
Classifier: Development Status :: 5 - Production/Stable
Classifier: Environment :: Web Environment
Classifier: Intended Audience :: Developers
Classifier: License :: OSI Approved :: MIT License
Classifier: Operating System :: OS Independent
Classifier: Programming Language :: Python
Classifier: Framework :: Django
License-File: LICENSE
License-File: AUTHORS
